setup.py
cinder_data/__init__.py
cinder_data/cache.py
cinder_data/model.py
cinder_data/store.py
cinder_data.egg-info/PKG-INFO
cinder_data.egg-info/SOURCES.txt
cinder_data.egg-info/dependency_links.txt
cinder_data.egg-info/top_level.txt