Metadata-Version: 1.0
Name: cinder-data
Version: 0.0.1
Summary: A port of the excellent ember-data library for Python projects.
Home-page: https://github.com/almcc/cinder-data
Author: Alastair McClelland
Author-email: alastair.mcclelland@gmail.com
License: MIT License
Keywords: ember cinder data rest json api client
Platform: UNKNOWN
